pycomfoconnect/__init__.py
pycomfoconnect/bridge.py
pycomfoconnect/comfoconnect.py
pycomfoconnect/const.py
pycomfoconnect/error.py
pycomfoconnect/message.py
pycomfoconnect/zehnder_pb2.py
pycomfoconnect-0.5.1.dist-info/LICENSE
pycomfoconnect-0.5.1.dist-info/METADATA
pycomfoconnect-0.5.1.dist-info/WHEEL
pycomfoconnect-0.5.1.dist-info/top_level.txt
pycomfoconnect-0.5.1.dist-info/RECORD
